fsllog/__init__.py
fsllog/fslog.py
fsllog-0.1.2.dist-info/licenses/LICENSE.txt
fsllog-0.1.2.dist-info/METADATA
fsllog-0.1.2.dist-info/WHEEL
fsllog-0.1.2.dist-info/top_level.txt
fsllog-0.1.2.dist-info/RECORD
