Metadata-Version: 2.4
Name: fsllog
Version: 0.1.2
Summary: Colorful logging library with log rotation and RGB support
Author-email: Fsain228 <Fsain30178@gmail.com>
Project-URL: Homepage, https://github.com/Fsain228/fslog
Project-URL: Repository, https://github.com/Fsain228/fslog.git
Classifier: Programming Language :: Python :: 3
Classifier: License :: OSI Approved :: MIT License
Classifier: Operating System :: OS Independent
Classifier: Intended Audience :: Developers
Classifier: Topic :: Software Development :: Libraries
Requires-Python: >=3.8
License-File: LICENSE.txt
Dynamic: license-file
